mubble/__init__.py
mubble/model.py
mubble/modules.py
mubble/msgspec_json.py
mubble/msgspec_utils.py
mubble/py.typed
mubble/rules.py
mubble/verification_utils.py
mubble/api/__init__.py
mubble/api/api.py
mubble/api/error.py
mubble/api/response.py
mubble/api/token.py
mubble/bot/__init__.py
mubble/bot/bot.py
mubble/bot/cute_types/__init__.py
mubble/bot/cute_types/base.py
mubble/bot/cute_types/callback_query.py
mubble/bot/cute_types/chat_join_request.py
mubble/bot/cute_types/chat_member_updated.py
mubble/bot/cute_types/inline_query.py
mubble/bot/cute_types/message.py
mubble/bot/cute_types/pre_checkout_query.py
mubble/bot/cute_types/update.py
mubble/bot/cute_types/utils.py
mubble/bot/dispatch/__init__.py
mubble/bot/dispatch/abc.py
mubble/bot/dispatch/context.py
mubble/bot/dispatch/dispatch.py
mubble/bot/dispatch/process.py
mubble/bot/dispatch/handler/__init__.py
mubble/bot/dispatch/handler/abc.py
mubble/bot/dispatch/handler/audio_reply.py
mubble/bot/dispatch/handler/base.py
mubble/bot/dispatch/handler/document_reply.py
mubble/bot/dispatch/handler/func.py
mubble/bot/dispatch/handler/media_group_reply.py
mubble/bot/dispatch/handler/message_reply.py
mubble/bot/dispatch/handler/photo_reply.py
mubble/bot/dispatch/handler/sticker_reply.py
mubble/bot/dispatch/handler/video_reply.py
mubble/bot/dispatch/middleware/__init__.py
mubble/bot/dispatch/middleware/abc.py
mubble/bot/dispatch/middleware/global_middleware.py
mubble/bot/dispatch/return_manager/__init__.py
mubble/bot/dispatch/return_manager/abc.py
mubble/bot/dispatch/return_manager/callback_query.py
mubble/bot/dispatch/return_manager/inline_query.py
mubble/bot/dispatch/return_manager/message.py
mubble/bot/dispatch/return_manager/pre_checkout_query.py
mubble/bot/dispatch/view/__init__.py
mubble/bot/dispatch/view/abc.py
mubble/bot/dispatch/view/base.py
mubble/bot/dispatch/view/box.py
mubble/bot/dispatch/view/callback_query.py
mubble/bot/dispatch/view/chat_join_request.py
mubble/bot/dispatch/view/chat_member.py
mubble-1.6.0.dist-info/METADATA
mubble-1.6.0.dist-info/WHEEL
mubble-1.6.0.dist-info/RECORD
