Metadata-Version: 2.4
Name: mubble
Version: 1.6.0
Summary: Modern Async Telegram framework for bot building
Project-URL: Source, https://github.com/vladislavkovalskyi/mubble
Project-URL: Documentation, https://github.com/vladislavkovalskyi/mubble
Author-email: vladislavkovalskyi <vladislavkovalskyi@icloud.com>
Maintainer-email: vladislavkovalskyi <vladislavkovalskyi@icloud.com>
Keywords: async,asyncio,best framework,bot api,bot building,bot building framework,mubble,mubble framework,telegram,telegram bot api,telegram framework
Classifier: Environment :: Console
Classifier: Intended Audience :: Developers
Classifier: License :: OSI Approved :: MIT License
Classifier: Programming Language :: Python :: 3.12
Classifier: Programming Language :: Python :: 3.13
Classifier: Topic :: Software Development :: Libraries :: Python Modules
Classifier: Topic :: Software Development :: Quality Assurance
Classifier: Typing :: Typed
Requires-Python: <4.0,>=3.12
Requires-Dist: aiohttp<4.0.0,>=3.11.11
Requires-Dist: certifi>=2025.1.31
Requires-Dist: choicelib<0.2.0,>=0.1.5
Requires-Dist: colorama<0.5.0,>=0.4.6
Requires-Dist: envparse<0.3.0,>=0.2.0
Requires-Dist: fntypes<0.2.0,>=0.1.4.post3
Requires-Dist: msgspec<0.20.0,>=0.19.0
Requires-Dist: typing-extensions<5.0.0,>=4.12.2
Requires-Dist: vbml<2.0,>=1.1.post1
Provides-Extra: all
Requires-Dist: loguru>=0.7.0; extra == 'all'
Requires-Dist: uvloop>=0.21.0; extra == 'all'
Provides-Extra: fast
Requires-Dist: uvloop>=0.21.0; extra == 'fast'
Provides-Extra: loguru
Requires-Dist: loguru>=0.7.0; extra == 'loguru'
Provides-Extra: uvloop
Requires-Dist: uvloop>=0.21.0; extra == 'uvloop'
